cocunimodule/__init__.py
cocunimodule/cocunirandom.py
cocuni_module-0.2.dist-info/LICENCE.txt
cocuni_module-0.2.dist-info/METADATA
cocuni_module-0.2.dist-info/WHEEL
cocuni_module-0.2.dist-info/top_level.txt
cocuni_module-0.2.dist-info/RECORD
