Metadata-Version: 2.1
Name: cocuni-module
Version: 0.2
Summary: A Python package for cocuni random numbers generation
Home-page: https://github.com/cocuni80/package
Author: Jorge Riveros
Author-email: christian.riveros@outlook.com
License: MIT
Platform: UNKNOWN
Classifier: Programming Language :: Python :: 3
Classifier: License :: OSI Approved :: MIT License
Classifier: Operating System :: OS Independent
Requires-Python: >=3.7
License-File: LICENCE.txt
Requires-Dist: requests
